curry_batch/__init__.py
curry_batch/__main__.py
curry_batch-0.4.2.dist-info/METADATA
curry_batch-0.4.2.dist-info/WHEEL
curry_batch-0.4.2.dist-info/entry_points.txt
curry_batch-0.4.2.dist-info/RECORD
