Metadata-Version: 2.1
Name: curry-batch
Version: 0.4.2
Summary: Curry a list of commands passed as arguments with a YAML list of argument lists, then output the command stdout as a new YAML list of lists.
License: MIT
Author: Ben Skubi
Author-email: bskubi@gmail.com
Requires-Python: >=3.12,<4.0
Classifier: License :: OSI Approved :: MIT License
Classifier: Programming Language :: Python :: 3
Classifier: Programming Language :: Python :: 3.12
Requires-Dist: pyyaml (>=6.0.1,<7.0.0)
